llama_index/embeddings/nvidia/__init__.py
llama_index/embeddings/nvidia/base.py
llama_index/embeddings/nvidia/utils.py
llama_index_embeddings_nvidia-0.4.2.dist-info/METADATA
llama_index_embeddings_nvidia-0.4.2.dist-info/WHEEL
llama_index_embeddings_nvidia-0.4.2.dist-info/licenses/LICENSE
llama_index_embeddings_nvidia-0.4.2.dist-info/RECORD
